ml_training_base/__init__.py
ml_training_base/data/__init__.py
ml_training_base/data/preprocessing/__init__.py
ml_training_base/data/preprocessing/base_data_preprocessors.py
ml_training_base/supervised/__init__.py
ml_training_base/supervised/data/__init__.py
ml_training_base/supervised/data/base_supervised_data_loader.py
ml_training_base/supervised/environments/__init__.py
ml_training_base/supervised/environments/base_training_environments.py
ml_training_base/supervised/trainers/__init__.py
ml_training_base/supervised/trainers/base_supervised_trainers.py
ml_training_base/utils/__init__.py
ml_training_base/utils/config_utils.py
ml_training_base/utils/files_utils.py
ml_training_base/utils/logging_utils.py
ml_training_base-0.4.0.dist-info/licenses/LICENSE
ml_training_base-0.4.0.dist-info/METADATA
ml_training_base-0.4.0.dist-info/WHEEL
ml_training_base-0.4.0.dist-info/top_level.txt
ml_training_base-0.4.0.dist-info/RECORD
