Metadata-Version: 2.4
Name: ml-training-base
Version: 0.4.0
Summary: A base library for ML training (supervised) with environment setup and logging.
Author-email: Chris van den Berg <cvandenberg1105@googlemail.com>
License: MIT
Keywords: machine-learning,training,tensorflow,keras,supervised-learning
Classifier: Programming Language :: Python :: 3
Classifier: Operating System :: OS Independent
Requires-Python: >=3.7
License-File: LICENSE
Requires-Dist: numpy>=1.23
Requires-Dist: tensorflow>=2.1
Requires-Dist: PyYAML>=6.0
Requires-Dist: torch>=2.7
Dynamic: license-file
